call_throttle/__init__.py
call_throttle/decorators.py
call_throttle/exceptions.py
call_throttle/throttle.py
call_throttle-0.4.0.dist-info/LICENSE
call_throttle-0.4.0.dist-info/METADATA
call_throttle-0.4.0.dist-info/WHEEL
call_throttle-0.4.0.dist-info/top_level.txt
call_throttle-0.4.0.dist-info/RECORD
