Metadata-Version: 2.1
Name: call-throttle
Version: 0.4.0
Summary: A decorator used to throttle calls of regular functions and asyncio coroutines.
Home-page: https://github.com/ktolstikhin/call-throttle.git
Author: Konstantin Tolstikhin
Author-email: k.tolstikhin@gmail.com
License: MIT
Keywords: decorator,throttle,ratelimit
Classifier: License :: OSI Approved :: MIT License
Classifier: Programming Language :: Python :: 3.7
Classifier: Operating System :: OS Independent
Classifier: Intended Audience :: Developers
Requires-Python: >=3.7
License-File: LICENSE
